dswe/AMK.py
dswe/_AMK_subroutine.py
dswe/_DNN_subroutine.py
dswe/_GPMethods.py
dswe/__init__.py
dswe/_comparePCurve_subroutine.py
dswe/_covmatch_subroutine.py
dswe/_funGP_subroutine.py
dswe/_knn_subroutine.py
dswe/_tempGP_subroutine.py
dswe/bayes_tree.py
dswe/comparePCurve.py
dswe/covmatch.py
dswe/dnn.py
dswe/funGP.py
dswe/knn.py
dswe/svm.py
dswe/tempGP.py
dswe/utils.py
dswe-0.1.3.dist-info/LICENSE
dswe-0.1.3.dist-info/METADATA
dswe-0.1.3.dist-info/WHEEL
dswe-0.1.3.dist-info/top_level.txt
dswe-0.1.3.dist-info/RECORD
