Metadata-Version: 2.1
Name: dswe
Version: 0.1.3
Summary: A python package to supplement the Data Science for Wind Energy (DSWE) book.
Home-page: https://tamu-aml.github.io/DSWE-Python/
Author: Pratyush Kumar, Abhinav Prakash, and Yu Ding
Author-email: yuding@tamu.edu
Maintainer-email: pratyush.019@gmail.com
License: MIT
Project-URL: Source, https://github.com/TAMU-AML/DSWE-Python
Project-URL: Bug Tracker, https://github.com/TAMU-AML/DSWE-Python/issues
Classifier: Programming Language :: Python :: 3
Classifier: Operating System :: OS Independent
Requires-Python: >=3.6
License-File: LICENSE
Requires-Dist: numpy (>=1.21.2)
Requires-Dist: pandas (>=1.3.3)
Requires-Dist: scikit-learn (>=1.0)
Requires-Dist: scipy (>=1.7.0)
Requires-Dist: statsmodels (>=0.13.0)
Requires-Dist: torch (>=1.0.0)
Requires-Dist: matplotlib (>=3.4.3)
